{"01K4zKU104LyJ8gMb7227B": {"s": 289201173, "d": 131060}, "03bTIHJElXZ0O0jqOQvAbY": {"s": 139239791, "d": 3259556}, "045ZeOHPIzhxxsm8bq5kyE": {"s": 224377878, "d": 248066}, "04S1pkp1VaIqjg8zZqknR5": {"s": 965016208, "d": 276089}, "05GsNucq8Bngd9fnd4fRa0": {"s": 149335060, "d": 105295}, "06zIBqLC9ZRm5i0iMf0kHI": {"s": 22014615, "d": 56345}, "07NxDD1iKCHbAldceD7QLP": {"s": 272507547, "d": 72804}, "08fa9LFcFBTcilB3iq2e2A": {"s": 226867336, "d": 70137}, "0CD7DzeCsuPJygddqlUVYa": {"s": 412859457, "d": 204796}, "0DMVrlMUn01M0IcpDbwgu7": {"s": 74670591, "d": 25432}, "0JIdBrXGSJXS72zjF9ss9u": {"s": 64755708, "d": 17767}, "0P9wLFurlgumLXuqFEpw52": {"s": 733409296, "d": 383919}, "0KztjtD3ytzgYjUKIVfBnW": {"s": 257666132, "d": 56483}, "0NRHj8hDwwmSPaA41o379r": {"s": 91209487, "d": 33649}, "0Nw8hv79MLJa1yjtsEgz08": {"s": 7441263, "d": 1329}, "0NwGC0v03ysCYINtg6ns58": {"s": 173935236, "d": 48898}, "1MgV7FIyNxIG7WzMRJV5HC": {"s": 777236629, "d": 531347}, "0Om9WAB5RS09L80DyOfTNa": {"s": 160211549, "d": 43137}, "0PurA4JVJ8YQgSVopY8fn6": {"s": 411003014, "d": 184714}, "0RdcBnAXyH2YZZvcBVu2k6": {"s": 29765317, "d": 5686}, "0TyGh27YQ5LknmiDhCzJiT": {"s": 144064481, "d": 106879}, "77d7q9TNbsIDmRTDPkPv3L": {"s": 18888530, "d": 7228}, "0UAdDYrkCvVQftaKpL6q5f": {"s": 54628567, "d": 14433}, "0V3wPSX9ygBnCm8psDIegu": {"s": 1917748733, "d": 477696}, "0VE4kBnHJUgtMf0dy6DRmW": {"s": 857581169, "d": 415869}, "0W0iAC1VGlB82PI6elxFYf": {"s": 495335232, "d": 390071}, "0XfTh16YcKPzdxMPTeKTAq": {"s": 15323302, "d": 3227}, "5jQyGzcwqAxwT5QUIMivoX": {"s": 549017607, "d": 266034}, "0cEG04R5cldkTLzK6phlcn": {"s": 18622813, "d": 3834}, "0cITLOYn1Sv4q27zZPqlNK": {"s": 284406650, "d": 79353}, "0cqRj7pUJDkTCEsJkx8snD": {"s": 1745105590, "d": 638698}, "0GxW5K0qzrq7L1jwSY5OmY": {"s": 55754118, "d": 7173}, "0g4fMVo4JjwnIpTfFfLdxS": {"s": 114602054, "d": 56004}, "2NIBaWXdjaTDmytjjwbEfP": {"s": 49139237, "d": 11235}, "0heeNYlwOGuUSe7TgUD27B": {"s": 350084471, "d": 119725}, "0k0vFacOHNuArLWMiH60p7": {"s": 72013282, "d": 17870}, "0q6vsjvnCIWrtwRckCV7y0": {"s": 90202456, "d": 37286}, "0lKUBmEyQfzsQHozyeXzES": {"s": 163313890, "d": 107351}, "0lx2cLdOt3piJbcaXIV74f": {"s": 1035100105, "d": 316840}, "0qUnBLZ8bJqUNEeQgayL9t": {"s": 353468025, "d": 80049}, "0qsSmObOgBZfuMIwfAQDBP": {"s": 73478707, "d": 11140}, "0sY6ZUTh4yoctD8VIXz339": {"s": 781710360, "d": 288467}, "0tQ9vBYpldCuikPsbgOVKA": {"s": 78860272, "d": 45580}, "0ug5NqcwcFR2xrfTkc7k8e": {"s": 1548065517, "d": 860205}, "0v4z1tuZvn6LGknom9Qx7d": {"s": 158575063, "d": 64036}, "0vqI4ZIMuifeKeItGiWbPj": {"s": 46801809, "d": 11169}, "0vvt4IZOMkRug195S4MUq0": {"s": 47911890, "d": 8629}, "0wAvTNz81YTUhLFWuWJSAV": {"s": 811486, "d": 7237}, "0y6kdSRCVQhSsHSpWvTUm7": {"s": 157992055, "d": 70225}, "0zo975x58DlXbZllWvfYhg": {"s": 106072053, "d": 30143}, "10GRRCR5fctuOF4GFmATJI": {"s": 167299590, "d": 81749}, "11UaQaEp2LvdspTyyuE3ur": {"s": 115037290, "d": 25783}, "12M5uqx0ZuwkpLp5rJim1a": {"s": 423655693, "d": 161140}, "12nBPF4Rh4XLFJV0YLN7uj": {"s": 64008821, "d": 22847}, "12ntTeqEeTg7GAVpe8Mhpl": {"s": 296099492, "d": 150267}, "15DeqWWQB4dcEWzJg15VrN": {"s": 437224068, "d": 152057}, "16M9Rxid0nXhVmme7lzVwN": {"s": 25805650, "d": 7768}, "16MVSD0mGI4RMQT83Qzm69": {"s": 151194932, "d": 42949}, "4P9Q0GojKVXpRTJCaL3kyy": {"s": 460673666, "d": 117834}, "18WFFUIsewmA8g31KAeo3e": {"s": 237220748, "d": 196084}, "19CSr8rwW05VJL2F91KFNK": {"s": 272866700, "d": 104271}, "1BxfuPKGuaTgP7aM0Bbdwr": {"s": 3118654882, "d": 1080751}, "1By2VQkUN0Frd8mKNV5NYC": {"s": 231499433, "d": 101983}, "1D27z8xNzjW0Mwwt1NCWhJ": {"s": 135302535, "d": 29471}, "1DTRUYVd8rYpla9hhVVwjo": {"s": 97760765, "d": 55661}, "1EQn3Uc5AyUXoiPLeyCrrg": {"s": 76731147, "d": 10931}, "1Fj0T1XKuhRu7EZzJ7NJIK": {"s": 49590017, "d": 20718}, "1GwMQaZz6Au3QLDbjbMdme": {"s": 534387261, "d": 323287}, "1HCdems7PQZRj42QDWLA0A": {"s": 121274483, "d": 49333}, "1J1ldDi3rMQlRi49gaba0a": {"s": 346699990, "d": 402599}, "1K39ty6o1sHwwlZwO6a7wK": {"s": 957481556, "d": 401336}, "1LLXZFeAHK9R4xUramtUKw": {"s": 413372222, "d": 143805}, "1P17dC1amhFzptugyAO7Il": {"s": 1376177282, "d": 326919}, "1QQii3pa5m8MEda0nbkjfw": {"s": 438029837, "d": 177499}, "1R0a2iXumgCiFb7HEZ7gUE": {"s": 1496437638, "d": 595579}, "1SmiQ65iSAbPto6gPFlBYm": {"s": 157246098, "d": 33580}, "1SymEzIT3H8UZfibCs3TYi": {"s": 483040135, "d": 141329}, "1SztNGCwEHJEVFx90E5g7D": {"s": 192074893, "d": 67226}, "3hUxzQpSfdDqwM3ZTFQY0K": {"s": 1674914072, "d": 891630}, "1ULabO0PEsdJekqVH6G10G": {"s": 111646522, "d": 48969}, "1XjHRolIXL2M1EEOUsGGR4": {"s": 242358150, "d": 112741}, "1ZY1PqizIl78geGM4xWlEA": {"s": 714475550, "d": 174119}, "1appZ3c336FkPvCuywfmrs": {"s": 112959133, "d": 2338325}, "1cJkUN5LAotktryx2nPCr7": {"s": 7280437, "d": 1540}, "1cSFlSBdpT4F5vb1frQ231": {"s": 92969497, "d": 28803}, "1dGr1c8CrMLDpV6mPbImSI": {"s": 1897242762, "d": 769001}, "1fzAuUVbzlhZ1lJAx9PtY6": {"s": 627386200, "d": 501775}, "1g09DZjQ7yBommCT6POY2n": {"s": 10198615, "d": 2347}, "1hR8BSuEqPCCZfv93zzzz9": {"s": 174138315, "d": 72662}, "1hjRhYpWyqDpPahmSlUTlc": {"s": 381451573, "d": 279961}, "1kTPQnabROVkW9bUXdCGrB": {"s": 117458001, "d": 22824}, "1kcwpPDQnqEqmezzXdJTCP": {"s": 227134500, "d": 177061}, "1msEuwSBneBKpVCZQcFTsU": {"s": 142081314, "d": 38975}, "1n2wszmJyVkw6FHqyLnQsY": {"s": 51602294, "d": 13801}, "1qLeEu4iXEclkLwoBlMiou": {"s": 61526280, "d": 13555}, "1qrpoAMXodY6895hGKoUpA": {"s": 991572783, "d": 527822}, "1rmEsOezwf2lmIZTMAO5Ag": {"s": 148058119, "d": 112982}, "1spLfUJxtyVyiKKTegQ2r4": {"s": 33291525, "d": 9641}, "1tuNqJOtRQVHvONR8Lg3MZ": {"s": 251840559, "d": 163694}, "1u4HUiREUR6vX1W1RYG2Tm": {"s": 16261814, "d": 5188}, "1u8c2t2Cy7UBoG4ArRcF5g": {"s": 2237143275, "d": 1023355}, "1wtOxkiel43cVs0Yux5Q4h": {"s": 503162614, "d": 139966}, "1xwAWUI6Dj0WGC3KiUPN0O": {"s": 494102927, "d": 131364}, "1yDJcXc549N6AabNBzFAku": {"s": 17199050, "d": 5452}, "1yFjBRQVhRdcdnrTE5LuyD": {"s": 121765107, "d": 26722}, "1zU8j1x3yi9xalMF96pzKp": {"s": 143241971, "d": 43438}, "1zxrcAk6eiytfavqriMcKT": {"s": 58797996, "d": 10818}, "20QSU9vg05qYSDVgOTAwPp": {"s": 266064, "d": 2612}, "214nt20w5wOxJnY462klLw": {"s": 519731544, "d": 368140}, "22bPsP2jCgbLUvh82U0Z3M": {"s": 546592194, "d": 272923}, "2913xXOVAIDAqxzV2g4VcU": {"s": 145760144, "d": 112557}, "2CYVETnhM9aytqrazYYwrK": {"s": 450988182, "d": 123874}, "2CnjDMdpRjlWv04Xk3s6MW": {"s": 86346829, "d": 61531}, "2EFZ9emtKWEglWUQGEQ3P9": {"s": 83030019, "d": 40728}, "4ojxSyrEraN7d46BMBPThZ": {"s": 440387512, "d": 134001}, "2F3N9tdombb64aW6VtZOdo": {"s": 480069616, "d": 318801}, "2IprIjGNRlj3TfqUWCAo0C": {"s": 38138234, "d": 9845}, "2JoJrsEV15OzbijS47lids": {"s": 69519359, "d": 20950}, "2L09RYwH5Pjzca6PmbUAw3": {"s": 348856548, "d": 172262}, "2NGGvVcfb2m2NbVaXHC3gb": {"s": 873435, "d": 7814}, "2NlmmAjGYrrjAp0MED5rGx": {"s": 705105722, "d": 241785}, "2NmsngXHeC1GQ9wWrzhOMf": {"s": 582656380, "d": 276977}, "2QA3IixpRcKyOdG7XDzRgv": {"s": 39705642, "d": 12171}, "2QDyYdZyhlP2fp79KZX8Bi": {"s": 264420649, "d": 82080}, "2QrQCMel6v2JiLxqrg4p2O": {"s": 60281766, "d": 19444}, "2R7C9dDqv1UPycvepBFziA": {"s": 27643871, "d": 4323}, "2TEQvxxQabwLQMqWMg1qGu": {"s": 118071799, "d": 2813575}, "2ULNeSomDxVNmdDy8VxEBU": {"s": 446582174, "d": 113714}, "2VuqMjgoKaOHNM8HpxtXKx": {"s": 358090622, "d": 142558}, "2XXwLdtuAcE0HSCu61ijAb": {"s": 369428162, "d": 282813}, "2YWtcWi3a83pdEg3Gif4Pd": {"s": 333502734, "d": 89823}, "2ZoOmCSgj0ypVAmGd1ve4y": {"s": 44738881, "d": 12978}, "2bzUVEvpZ7At5cYz1kOLI9": {"s": 84358025, "d": 55624}, "2dgFqt3w9xIQRjhPtwNk3D": {"s": 354519829, "d": 124555}, "2hmafYGj1CXYKIYcMnX4lj": {"s": 45796214, "d": 10740}, "2m3ObD945KvpE5y9A1eUWm": {"s": 73110519, "d": 22488}, "2nqio0SfWg6gh2eCtfuMa5": {"s": 127919253, "d": 34534}, "2o2sgVJIgFXk8GQjWTgI6U": {"s": 246931633, "d": 111652}, "2r9CbjYgFhtAmcFv1cSquB": {"s": 118778555, "d": 53842}, "6KJqZcs9XDgVck7Lg9QOTC": {"s": 391526812, "d": 136271}, "2wtHlpYSgC7xEdD3DrSHNL": {"s": 47003959, "d": 11447}, "2x0WlnmfG39ZuDmstl9xfX": {"s": 598155649, "d": 157619}, "2x3mwb96B6TquRqMtbxUE1": {"s": 113581302, "d": 2441395}, "2yLa0QULdQr0qAIvVwN6B5": {"s": 959080079, "d": 382547}, "2zfgVd034GlUvk7LqBHl6u": {"s": 143472311, "d": 19779}, "30Y4CV7A6YqtQtTTo7Ue4j": {"s": 133493616, "d": 37124}, "31JVjy3XWnh6C2zf4kLCXN": {"s": 8527587, "d": 1592}, "32mVHdy0bi1XKgr0ajsBlG": {"s": 243898965, "d": 68283}, "34V9RiEPe8MNdU32qJsJa1": {"s": 73262120, "d": 14809}, "35rdVq36LMHQX0Suw9a6tK": {"s": 150685491, "d": 48176}, "3AKV7Mvo2Mx4tb39iPvPlT": {"s": 154334541, "d": 3482111}, "3CCRVu4F91Qp2mnGjmWBrf": {"s": 265812086, "d": 114619}, "3CWq0pAKKTWb0K4yiglDc4": {"s": 354269250, "d": 205501}, "3ExweHKZF9B752DPQByRVT": {"s": 56444340, "d": 14713}, "3JilapcaOXzjR9gtvCY8FO": {"s": 96443011, "d": 20408}, "3K2es3gElMRJ3qvmPW442g": {"s": 152062047, "d": 24307}, "3MytWN8L7shNYzGl4tAKRp": {"s": 176173731, "d": 70346}, "3NMrVbIVWT3fPXBj0rNDKG": {"s": 306521138, "d": 148433}, "3O5osWf1rSoKMwe6E9ZaXP": {"s": 280979702, "d": 141409}, "3RaT22zZsxVYxxKR7TAaYF": {"s": 334893847, "d": 101118}, "3RauEVgRgj1IuWdJ9fDs70": {"s": 964705081, "d": 250724}, "3S7HNKPakdwNEBFIVTL6dZ": {"s": 138962525, "d": 54960}, "3Vevii7qKqrmW8CcyzBHDl": {"s": 388378659, "d": 216297}, "3YkNIrAvbKNrrwwEd7NVLl": {"s": 315545737, "d": 332691}, "3eX0NZfLtGzoLUxPNvRfqm": {"s": 576121251, "d": 318338}, "3fO566xJgwxIa3qGCGBvIC": {"s": 229295159, "d": 153540}, "3hlGuz3loYoLfI3bpwieWq": {"s": 158465199, "d": 104110}, "3k7ne7VmH43ZPWxPdvPUgR": {"s": 222059211, "d": 77829}, "3kfgJql90tzgoxByioAMXR": {"s": 56035135, "d": 8522}, "3lXekiVK1ZPZbKconsys73": {"s": 51039262, "d": 10587}, "3nRmDz7qGCvsMS30rGGY0x": {"s": 281153616, "d": 101350}, "3nsfB1vus2qaloUdcBZvDu": {"s": 352083540, "d": 197257}, "3oGVx9RBmiYGv5ZCecWLkx": {"s": 117324226, "d": 43940}, "3pHkh7d0lzM2AldUtz2x37": {"s": 519743013, "d": 209641}, "3pv7Q5v2dpdefwdWIvE7yH": {"s": 210050392, "d": 91395}, "3qoftcUZaUOncvIYjFSPdE": {"s": 680501510, "d": 260865}, "3r9fAceWmaDFvbNiTnFiLr": {"s": 994290, "d": 8621}, "3rWDp9tBPQR9z6U5YyRSK4": {"s": 813188308, "d": 245322}, "3sW3oSbzsfecv9XoUdGs7h": {"s": 467279168, "d": 291785}, "3xYJScVfxByb61dYHTwiby": {"s": 266778636, "d": 129392}, "3yII7UwgLF6K5zW3xad3MP": {"s": 389837605, "d": 122764}, "3yNJkriPzWjkkDAWHIAVUq": {"s": 77943562, "d": 28116}, "3yWuTOYDztXjZxdE2cIRUa": {"s": 196217811, "d": 5702936}, "3z6XUommYDWPHeFhmhhT6j": {"s": 260782139, "d": 148722}, "3zMDGj4D8ogaYgAIZPeU7S": {"s": 152667799, "d": 116820}, "42TAweWJJ9YlQ47T5nesu5": {"s": 598677, "d": 5763}, "43rA71bccXFGD4C8GOpIlN": {"s": 396707749, "d": 126991}, "43y1WpBdnEy5TR9aZoSQL9": {"s": 129315586, "d": 56998}, "45R112Jz5hQeKgITXgSXzs": {"s": 970093236, "d": 305013}, "45wMBGri1PORPjM9PwFfrS": {"s": 331689306, "d": 143338}, "46NGAvL695VnbcSeTmQWmM": {"s": 203170758, "d": 41919}, "48A0aShHlovDfTMucMrE66": {"s": 140743826, "d": 31899}, "4A2LfnduSTsE8u0ecYROxE": {"s": 155527741, "d": 31596}, "4A4A6dwl5DqdqrZaEtKGPR": {"s": 1114140434, "d": 328907}, "4ABYxlb92WBIjHu7TIKmml": {"s": 113620600, "d": 37007}, "4AYtqFyFbX0Xkc2wtcygTr": {"s": 175006732, "d": 49184}, "4CHpVfAhuxNJ3ibExe6kxO": {"s": 130992381, "d": 20776}, "4CkgMiMqZ5JzW9iYXSTMTL": {"s": 276324517, "d": 106711}, "4D7BCuvgdJlYvlX5WlN54t": {"s": 799296533, "d": 470050}, "4EF6IyONolQy0bIQXm2EmX": {"s": 133963517, "d": 66039}, "4IQkfUsrwXol38VV3U7t7T": {"s": 164298867, "d": 46159}, "4N419mmxYybTfAECy5j4dw": {"s": 50083999, "d": 8240}, "4OAuvHryIVv4kMDNSLuPt6": {"s": 406467537, "d": 225282}, "4OmFmE0fzcMG6g0Y8p4eSD": {"s": 187859722, "d": 89555}, "4R2kfaDFhslZEMJqAFNpdd": {"s": 1844603224, "d": 1078805}, "4WBEj8TeGtRPNJdOmT3WJW": {"s": 342781440, "d": 185716}, "4XMP3zVxrnr58T0tjIHvpR": {"s": 266757094, "d": 40402}, "4bBDkw2KBMX0tcgAaXC83Q": {"s": 368776145, "d": 206839}, "4bXCcoesMt8u99xMsbLr9U": {"s": 210799448, "d": 37803}, "4d9PtIEVij9jW5OaLinH66": {"s": 163145380, "d": 75508}, "4dgf2DYVJbtmy8zAYLs4c7": {"s": 741257524, "d": 642804}, "4e3ZNTAV6PCrdYMUrUlMpQ": {"s": 119016504, "d": 38168}, "4e5ayHsOLJNLTGfjau2mEw": {"s": 96695703, "d": 33750}, "4evLyY5Ue1Wesc61t2KXAU": {"s": 54766108, "d": 19548}, "4fWDgRZa0GKE5KZNhE9MQa": {"s": 54116408, "d": 10425}, "4i6cwNY6oIUU2XZxPIw82Y": {"s": 110416224, "d": 30296}, "4mKye6Z1kXuKolzMkJoKFA": {"s": 239437244, "d": 40611}, "4pFvEWbjBpPUdYRQly0THs": {"s": 34327020, "d": 6634}, "4pJi1rVt9GNegU9kywjg4z": {"s": 44202327, "d": 16523}, "4pNApnaUWAL2J4KO2eqokq": {"s": 148864307, "d": 75231}, "4pvb0WLRcMtbPGmtejJJ6y": {"s": 1046068150, "d": 605326}, "4qUijfYU8EoIWiY6oSyrgT": {"s": 68692647, "d": 13555}, "4qmFC3Jz5aQ0erlk2OSi2X": {"s": 92541048, "d": 1969533}, "4qyalTRMRH5YuEntvvMvq0": {"s": 45740356, "d": 10495}, "4s8BIKx4Zh6ryAEz8RTlaU": {"s": 128883878, "d": 48923}, "4svZDCRz4cJoneBpjpx8DJ": {"s": 551932130, "d": 158210}, "4tMzIAFTFdqGBQLdfbPces": {"s": 118969531, "d": 47912}, "4txojlesMFQZGWxwz2EeqB": {"s": 344506587, "d": 141813}, "4uuEGH5SVuzkkSFjo2DEiY": {"s": 89340353, "d": 24254}, "4y5bvROuBDPr5fuwXbIBZR": {"s": 795463903, "d": 218218}, "4yf9OivCH2lmQWN8mzpCC6": {"s": 128291209, "d": 23217}, "4zmKGsrXjLmljb5fTaBTot": {"s": 279870610, "d": 149813}, "50ho0AOvkm8E5l8zf7OfJI": {"s": 12995992, "d": 2532}, "51A8eKvvZz9uydvIZ7xRSV": {"s": 46419714, "d": 12514}, "53iuhJlwXhSER5J2IYYv1W": {"s": 288862675, "d": 9168782}, "550erGcdD9n6PnwxrvYqZT": {"s": 114378562, "d": 34923}, "59KOoHFcw5XfICnO57holu": {"s": 124971914, "d": 79595}, "5AsmAjBSSQjRPWgAYIp8tm": {"s": 33744003, "d": 6933}, "5BK0uqwY9DNfZ630STAEaq": {"s": 345258827, "d": 101237}, "5Bedn0svl0ZD7RGmJkmKKw": {"s": 196818303, "d": 140966}, "5EwypOO9NEI7MvjPOYZtWk": {"s": 585435, "d": 5546}, "5F7hpFKLmWgMHGxQuwssuv": {"s": 10315259, "d": 2984}, "5M787RexsAiVYjQusM98CV": {"s": 206390986, "d": 77925}, "5OOd01o2YS1QFwdpVLds3r": {"s": 44139430, "d": 12457}, "5PxFv9yJEg9dxvbZggykro": {"s": 234908351, "d": 85978}, "5QKhg4r4Ibt0LVTmWEXTEg": {"s": 42723876, "d": 11938}, "5QUIK7ZtziW8kGWo8RqopF": {"s": 407851960, "d": 139138}, "5SkuikJwvwfEvNyCepGkq3": {"s": 916672, "d": 7897}, "5VwFkx7JOimOGTYfha5rs1": {"s": 65981468, "d": 13737}, "5YL553x8sHderRBDlm3NM3": {"s": 142035928, "d": 92265}, "5YbZZ2gYfvW1UvHHF4pVaD": {"s": 44444406, "d": 9343}, "5YqltLsjdqFtvqE7Nrysvs": {"s": 465746381, "d": 126411}, "5chnRTB9qMK3W1M41SnU9s": {"s": 173204210, "d": 76440}, "5d2Kn9oAAh9S2EbyCo1i52": {"s": 58621814, "d": 16408}, "5eGX87IiKsGuzS3iw4CfCX": {"s": 79810042, "d": 14822}, "5gRYrtvyVyaCRvLt56OfuV": {"s": 163963304, "d": 29007}, "5hQSXkFgbxjZo9uCwd11so": {"s": 336554645, "d": 310853}, "5jQI2r1RdgtuT8S3iG8zFC": {"s": 856833375, "d": 225597}, "5k9RjjuYyOMCLL81U8FaHT": {"s": 1129819, "d": 8938}, "5kHMfzgLZP95O9NBy0ku4v": {"s": 327473503, "d": 89356}, "5kI4eCXXzyuIUXjQra0Cxi": {"s": 440743261, "d": 114910}, "5kYFVSQoPu7yRpfiHBwMUk": {"s": 59180420, "d": 16225}, "5l6GqSxplqnZbLg0LTPQeG": {"s": 471380576, "d": 183597}, "5lA0yK8S5tP3xoaRMCp4Ug": {"s": 4550117, "d": 531}, "5og4Qzt92jJzVDkOtSEilb": {"s": 346994315, "d": 163802}, "5tWxKWq1DSP1s9WQ5PWuqu": {"s": 230429001, "d": 86918}, "5vyxXfD5gLlyPxGZMEjtmd": {"s": 137666441, "d": 48674}, "5xPsybHWRHbTYO44xnREY5": {"s": 1054454636, "d": 356584}, "5xXqyjLicvEpch72qEryFT": {"s": 139221174, "d": 43895}, "5ylJtmaWPJ33cW3En7WOu0": {"s": 116859243, "d": 2521791}, "5yrrh7VYFMCNjUOIMzGNp5": {"s": 686375, "d": 7019}, "60hGQrn24APqEFSLObLeDc": {"s": 275330891, "d": 94210}, "60oZARTE1kCh5ntBfeO1XB": {"s": 5170790, "d": 68900}, "62E2nR0od0M5HYxuYLaDz7": {"s": 193374819, "d": 124847}, "62HoDY1Km6lm47haFpUn9c": {"s": 108656575, "d": 2193561}, "62V2ZHslgQV98gH4AuVXnr": {"s": 104930665, "d": 2215489}, "64FzgoLZ3oXu2SriZblHic": {"s": 141665508, "d": 64221}, "670fUmXf4KQekzbEgaXyPA": {"s": 218503489, "d": 90095}, "6AtZLIzUINvExIUy4QhdjP": {"s": 480571775, "d": 133367}, "6FJemhBlVTGTCgrrrLam3D": {"s": 738676, "d": 6586}, "6GXgd1BPD9bUpqw5AntGV5": {"s": 148496877, "d": 76080}, "6HRsJu8vcnzYDN4t0570FY": {"s": 114071738, "d": 53858}, "6IG3sQ8s9nfk6TUlVzRhbN": {"s": 555739261, "d": 176988}, "6JNM6pLKbXMGG2opeExCb2": {"s": 682745, "d": 6923}, "6K0CJLVXqbGMeJSmJ4ENKK": {"s": 43149751, "d": 12735}, "6LZaxlycSWrJZ4Volb25qx": {"s": 245518106, "d": 44340}, "6M9ppdfFjR1AbpUl3Y8DcV": {"s": 151388728, "d": 52413}, "6MWoRt97mnSTXZhu3ggi9C": {"s": 234883813, "d": 93079}, "6NFyWDv5CjfwuzoCkw47Xf": {"s": 1240705555, "d": 482498}, "6NUy8xajng5zMSGJRKniAG": {"s": 736819, "d": 6679}, "6ON9UuIq49xXY9GPmHIYRp": {"s": 67724323, "d": 20696}, "6RRNNciQGZEXnqk8SQ9yv5": {"s": 1096801004, "d": 198202}, "6SYwJcqaltK2WFRmD1unUV": {"s": 8401325, "d": 1589}, "6VsvKPJ4xjVNKpI8VVZ3SV": {"s": 495140171, "d": 282630}, "6WWvcA62QlnRguluWAk6bv": {"s": 28010749, "d": 5511}, "6YvqWjhGD8mB5QXcbcUKtx": {"s": 1084948512, "d": 540549}, "6aLOekfwbytwWvQftxTEF0": {"s": 239015349, "d": 51940}, "6cf6rLb8qcklvJv90W6HCW": {"s": 24788805, "d": 6322}, "6dTA6y0C2ReQklntzZl8l3": {"s": 138597207, "d": 55683}, "6iWMI5oOhWrDbLbjmwTWFq": {"s": 162284230, "d": 26150}, "6iiAfo4wTA2CVC3Uwx9uh8": {"s": 94028872, "d": 29556}, "6kl8thRysTeVV3WvKxgZAy": {"s": 397892830, "d": 205371}, "6lzc0Al0zfZOIFsFvBS1ki": {"s": 155140548, "d": 58559}, "6oVxXO5oQ4pTpO8RSnkzvv": {"s": 481803369, "d": 725092}, "6ovFJkdau79DuXEvQjPaNH": {"s": 25429074, "d": 6009}, "6pYNq0ZwpPVazKzsqpf0G8": {"s": 218254581, "d": 70067}, "6qAcApH8obo8eqatCKUHd9": {"s": 130556886, "d": 42659}, "6rZVy6FIG7lSJQMFXHo12z": {"s": 316389821, "d": 74220}, "6sQckd3Z8NPxVVKUnavY1F": {"s": 324579323, "d": 100371}, "6vLpy7UPYuOa75Bkqocrcw": {"s": 34491600, "d": 6634}, "6wfugRLamFsTRbPcCpNnP7": {"s": 188133499, "d": 41730}, "6xsEAm6w9oMQYYg3jkEkMT": {"s": 217090554, "d": 61327}, "6zV8AVM9eVfdG7Qahwd64R": {"s": 141188990, "d": 47212}, "71CBDRKmF2VeRKYMG1DFBh": {"s": 237316108, "d": 111057}, "71IScwIe7bcIlpnlkbKVQw": {"s": 14798469, "d": 2376}, "72jCZdH0Lhg93z6Z4hBjgj": {"s": 1027925026, "d": 466330}, "733OhaXQIHY7BKtY3vnSkn": {"s": 114028302, "d": 60637}, "73OX8GdpOeGzKC6OvGSbsv": {"s": 54095257, "d": 16420}, "73W5aXorr5vxrySFcoZqIN": {"s": 172237252, "d": 101358}, "73YUReisjb3A9ActdLLjJQ": {"s": 231701569, "d": 90400}, "73qMN9bXy7MSPwwGfH3wQr": {"s": 128051345, "d": 65488}, "77VotUUL79U10TAnYdqwvr": {"s": 80025671, "d": 24369}, "77sMIMlNaSURUAXq5coCxE": {"s": 431693067, "d": 175914}, "786NsUYn4GGUf8AOt0SQhP": {"s": 66241049, "d": 21898}, "79uDOz0zuuWS7HWxzMmTa2": {"s": 279458358, "d": 124000}, "7A2cNLRT0YJc1yjxHlKihs": {"s": 90097016, "d": 32042}, "7AEAGTc8cReDqcbPoY9gwo": {"s": 768260612, "d": 189605}, "7C0w28EsX0Um2FrZs9gso2": {"s": 151976752, "d": 54307}, "7F5oktn5YOsR9eR5YsFtqb": {"s": 255860246, "d": 91069}, "7G0gBu6nLdhFDPRLc0HdDG": {"s": 260833866, "d": 101226}, "7G6TDmGJXDoBaV6NGj3Yic": {"s": 769867344, "d": 297929}, "7GZ3KDorsc1yWndEtzGTjf": {"s": 7558564, "d": 1269}, "7HC7R2D8WjXVcUHJyEGjRs": {"s": 85586578, "d": 23877}, "7HuBDWi18s4aJM8UFnNheH": {"s": 349818515, "d": 166928}, "7I7JbDv63ZJJsSi24DyJrz": {"s": 323070680, "d": 191679}, "7J4b3LVCIGO4CMBDFLPoP6": {"s": 112627498, "d": 45156}, "7MbT4I8qGntX4fMdqMQgke": {"s": 260618514, "d": 97372}, "7an1exwMnfYRcdVQm0yDev": {"s": 55510229, "d": 17978}, "7dXKdjpOaH2iwfFKmUj7aq": {"s": 157990341, "d": 26892}, "7eQj6r5PIdYKEIZjucBMcq": {"s": 109485413, "d": 31374}, "7eResoqEJJAVTkQYSqvO3P": {"s": 98806008, "d": 21020}, "7gdwoOmi258QJq0hmQ4hto": {"s": 302644052, "d": 73826}, "7kt9e9LFSpN1zQtYEl19o1": {"s": 542807975, "d": 296522}, "7nWui6jiMM2m9qFmET1Mtj": {"s": 55608141, "d": 19226}, "7qEUFOVcxRI19tbT68JcYK": {"s": 220265953, "d": 138464}, "7vvIpJZye5cRR6De1LKM0m": {"s": 71419751, "d": 15217}, "7wo2UNeQBowm28hfAJsEMz": {"s": 18263461, "d": 11619}}