{"01K4zKU104LyJ8gMb7227B": {"s": 290928120, "d": 88087}, "01QdEx6kFr78ZejhQtWR5m": {"s": 66361403, "d": 15783}, "03bTIHJElXZ0O0jqOQvAbY": {"s": 178305516, "d": 1555783}, "045ZeOHPIzhxxsm8bq5kyE": {"s": 228327759, "d": 196356}, "04S1pkp1VaIqjg8zZqknR5": {"s": 969463499, "d": 250911}, "04xrhDrQ2WOW8GLwu7kbc0": {"s": 13894607, "d": 4742}, "05GsNucq8Bngd9fnd4fRa0": {"s": 150805267, "d": 80568}, "05kJkr80XEaZeN8kxyQoFp": {"s": 32774355, "d": 7909}, "06zIBqLC9ZRm5i0iMf0kHI": {"s": 22683935, "d": 35724}, "07NxDD1iKCHbAldceD7QLP": {"s": 273541553, "d": 48781}, "08J4bMHbILkwSIhbtrcvjN": {"s": 23289888, "d": 7579}, "08fa9LFcFBTcilB3iq2e2A": {"s": 234444590, "d": 4228}, "0CD7DzeCsuPJygddqlUVYa": {"s": 416076408, "d": 168775}, "0DMVrlMUn01M0IcpDbwgu7": {"s": 75042040, "d": 17634}, "0GxW5K0qzrq7L1jwSY5OmY": {"s": 55868242, "d": 5577}, "0JIdBrXGSJXS72zjF9ss9u": {"s": 65039647, "d": 13952}, "0P9wLFurlgumLXuqFEpw52": {"s": 772083357, "d": 7579}, "0KztjtD3ytzgYjUKIVfBnW": {"s": 258544242, "d": 43183}, "0NRHj8hDwwmSPaA41o379r": {"s": 91704375, "d": 24952}, "0Nw8hv79MLJa1yjtsEgz08": {"s": 7462390, "d": 1046}, "0NwGC0v03ysCYINtg6ns58": {"s": 174678905, "d": 37395}, "1MgV7FIyNxIG7WzMRJV5HC": {"s": 834861266, "d": 11693}, "0Om9WAB5RS09L80DyOfTNa": {"s": 160861553, "d": 33431}, "0PurA4JVJ8YQgSVopY8fn6": {"s": 413674466, "d": 140848}, "0QTBsdoJhamY3Aid3fOsOd": {"s": 15623384, "d": 4801}, "0RdcBnAXyH2YZZvcBVu2k6": {"s": 29851725, "d": 4364}, "0ThxqUZ9PwS6n0UT5i1XH6": {"s": 2955165, "d": 735}, "0TyGh27YQ5LknmiDhCzJiT": {"s": 145862418, "d": 96352}, "0U0etHtpARihOUUY8Akc7y": {"s": 19002610, "d": 5809}, "0UAdDYrkCvVQftaKpL6q5f": {"s": 54851537, "d": 11136}, "0V3wPSX9ygBnCm8psDIegu": {"s": 1925061622, "d": 346482}, "0VE4kBnHJUgtMf0dy6DRmW": {"s": 863653966, "d": 279987}, "0W0iAC1VGlB82PI6elxFYf": {"s": 501392225, "d": 323635}, "0XfTh16YcKPzdxMPTeKTAq": {"s": 15373555, "d": 2534}, "5jQyGzcwqAxwT5QUIMivoX": {"s": 576558236, "d": 7344}, "0cEG04R5cldkTLzK6phlcn": {"s": 18683151, "d": 2960}, "0cITLOYn1Sv4q27zZPqlNK": {"s": 285490920, "d": 52351}, "0cqRj7pUJDkTCEsJkx8snD": {"s": 1756076367, "d": 565738}, "0g4fMVo4JjwnIpTfFfLdxS": {"s": 115424372, "d": 38739}, "2NIBaWXdjaTDmytjjwbEfP": {"s": 49312798, "d": 8542}, "0hFF0aqyjDwDh6SQwRbTyx": {"s": 7162955, "d": 4118}, "0heeNYlwOGuUSe7TgUD27B": {"s": 351512070, "d": 62622}, "0hhzNPE68LWLfgZwdpxVdR": {"s": 256836182, "d": 194045}, "0k0vFacOHNuArLWMiH60p7": {"s": 72290960, "d": 13895}, "0q6vsjvnCIWrtwRckCV7y0": {"s": 90766915, "d": 28013}, "0lJWmQO1fw1Tr2p2M1m5cw": {"s": 84218890, "d": 14428}, "0lKUBmEyQfzsQHozyeXzES": {"s": 164865847, "d": 73963}, "0lx2cLdOt3piJbcaXIV74f": {"s": 1039961068, "d": 245613}, "0qUnBLZ8bJqUNEeQgayL9t": {"s": 354612147, "d": 56003}, "0qsSmObOgBZfuMIwfAQDBP": {"s": 73648780, "d": 8560}, "0sY6ZUTh4yoctD8VIXz339": {"s": 786118889, "d": 228171}, "0tQ9vBYpldCuikPsbgOVKA": {"s": 79561962, "d": 35164}, "0ug5NqcwcFR2xrfTkc7k8e": {"s": 1561897966, "d": 732915}, "0v4z1tuZvn6LGknom9Qx7d": {"s": 159543584, "d": 47288}, "0vqI4ZIMuifeKeItGiWbPj": {"s": 46932687, "d": 6357}, "0vvt4IZOMkRug195S4MUq0": {"s": 48052229, "d": 6670}, "0wAvTNz81YTUhLFWuWJSAV": {"s": 939424, "d": 5370}, "0y6kdSRCVQhSsHSpWvTUm7": {"s": 159124230, "d": 53324}, "0yisH8r0f3Mkq34kjzUlCV": {"s": 5132995, "d": 398}, "0zo975x58DlXbZllWvfYhg": {"s": 106537154, "d": 23502}, "10GRRCR5fctuOF4GFmATJI": {"s": 168374924, "d": 51656}, "11UaQaEp2LvdspTyyuE3ur": {"s": 115446677, "d": 18514}, "12M5uqx0ZuwkpLp5rJim1a": {"s": 426174520, "d": 122260}, "12nBPF4Rh4XLFJV0YLN7uj": {"s": 64371426, "d": 18473}, "12ntTeqEeTg7GAVpe8Mhpl": {"s": 298361605, "d": 122647}, "13MAWVUSkbGMUi6I7RowRK": {"s": 29344908, "d": 3397}, "15DeqWWQB4dcEWzJg15VrN": {"s": 439656690, "d": 130677}, "16M9Rxid0nXhVmme7lzVwN": {"s": 25925333, "d": 5893}, "16MVSD0mGI4RMQT83Qzm69": {"s": 151850420, "d": 30903}, "4P9Q0GojKVXpRTJCaL3kyy": {"s": 462464047, "d": 90818}, "18WFFUIsewmA8g31KAeo3e": {"s": 240192255, "d": 149596}, "19CSr8rwW05VJL2F91KFNK": {"s": 274561587, "d": 84033}, "1BxfuPKGuaTgP7aM0Bbdwr": {"s": 3136631170, "d": 923024}, "1By2VQkUN0Frd8mKNV5NYC": {"s": 233120507, "d": 80699}, "1D27z8xNzjW0Mwwt1NCWhJ": {"s": 135784476, "d": 24961}, "1DTRUYVd8rYpla9hhVVwjo": {"s": 98598188, "d": 41021}, "1EQn3Uc5AyUXoiPLeyCrrg": {"s": 76891396, "d": 7244}, "1Fj0T1XKuhRu7EZzJ7NJIK": {"s": 49911220, "d": 15621}, "1GwMQaZz6Au3QLDbjbMdme": {"s": 539256192, "d": 239141}, "1HCdems7PQZRj42QDWLA0A": {"s": 122047527, "d": 40661}, "1J1ldDi3rMQlRi49gaba0a": {"s": 352999657, "d": 330467}, "1K39ty6o1sHwwlZwO6a7wK": {"s": 963878127, "d": 304089}, "1LLXZFeAHK9R4xUramtUKw": {"s": 415519484, "d": 109923}, "1MaqkdFNIKPdpQGDzme5ss": {"s": 166709881, "d": 45080}, "1P17dC1amhFzptugyAO7Il": {"s": 1382151942, "d": 247188}, "1QQii3pa5m8MEda0nbkjfw": {"s": 440364576, "d": 105419}, "1R0a2iXumgCiFb7HEZ7gUE": {"s": 1505830396, "d": 430930}, "1SmiQ65iSAbPto6gPFlBYm": {"s": 157765017, "d": 26206}, "1SymEzIT3H8UZfibCs3TYi": {"s": 485459948, "d": 138493}, "1SztNGCwEHJEVFx90E5g7D": {"s": 192974702, "d": 41726}, "3hUxzQpSfdDqwM3ZTFQY0K": {"s": 1769742741, "d": 15598}, "1ULabO0PEsdJekqVH6G10G": {"s": 112378675, "d": 35321}, "1XjHRolIXL2M1EEOUsGGR4": {"s": 244172721, "d": 89138}, "1ZY1PqizIl78geGM4xWlEA": {"s": 717102708, "d": 130340}, "1Zai5UJ2di3qEuR2HeT2s8": {"s": 121651040, "d": 47408}, "1alAo6dYalSx8yZUn17JxF": {"s": 2680763, "d": 1651}, "1appZ3c336FkPvCuywfmrs": {"s": 141206055, "d": 1094320}, "1cJkUN5LAotktryx2nPCr7": {"s": 7334356, "d": 5517}, "1cSFlSBdpT4F5vb1frQ231": {"s": 93405882, "d": 20987}, "1dGr1c8CrMLDpV6mPbImSI": {"s": 1909791894, "d": 626941}, "1fzAuUVbzlhZ1lJAx9PtY6": {"s": 635214612, "d": 403127}, "1g09DZjQ7yBommCT6POY2n": {"s": 10277889, "d": 7965}, "1gaLZjPrDnHQWJds2Jg4KT": {"s": 27016383, "d": 12215}, "1gejz5ROvJBUb6WJzkMAcc": {"s": 37135915, "d": 19766}, "1hR8BSuEqPCCZfv93zzzz9": {"s": 175342287, "d": 65241}, "1hjRhYpWyqDpPahmSlUTlc": {"s": 385988570, "d": 271145}, "4GS68CE8nKLIKjjapiSm2I": {"s": 11077733, "d": 1466}, "1kTPQnabROVkW9bUXdCGrB": {"s": 117816576, "d": 17818}, "1kcwpPDQnqEqmezzXdJTCP": {"s": 229358165, "d": 123306}, "1mh5dObNoOvCfHmXnhvDEK": {"s": 16063463, "d": 4385}, "1msEuwSBneBKpVCZQcFTsU": {"s": 142672286, "d": 28554}, "1n2wszmJyVkw6FHqyLnQsY": {"s": 51818436, "d": 10796}, "1n3b9Eekoy3S9ZSZ5DmTW1": {"s": 68125308, "d": 36253}, "1qLeEu4iXEclkLwoBlMiou": {"s": 61678964, "d": 7105}, "1qrpoAMXodY6895hGKoUpA": {"s": 1000126852, "d": 456782}, "1rmEsOezwf2lmIZTMAO5Ag": {"s": 149706142, "d": 80446}, "1spLfUJxtyVyiKKTegQ2r4": {"s": 33447187, "d": 7629}, "1tuNqJOtRQVHvONR8Lg3MZ": {"s": 254272697, "d": 119335}, "1u4HUiREUR6vX1W1RYG2Tm": {"s": 16342015, "d": 4181}, "1u8c2t2Cy7UBoG4ArRcF5g": {"s": 2253864986, "d": 851678}, "1wtOxkiel43cVs0Yux5Q4h": {"s": 505083969, "d": 93383}, "1xwAWUI6Dj0WGC3KiUPN0O": {"s": 495968026, "d": 88881}, "1yDJcXc549N6AabNBzFAku": {"s": 17281076, "d": 3941}, "1yFjBRQVhRdcdnrTE5LuyD": {"s": 122189833, "d": 24039}, "1zU8j1x3yi9xalMF96pzKp": {"s": 143932137, "d": 34168}, "1zxrcAk6eiytfavqriMcKT": {"s": 58966587, "d": 8586}, "20QSU9vg05qYSDVgOTAwPp": {"s": 323545, "d": 2322}, "214nt20w5wOxJnY462klLw": {"s": 524994343, "d": 265975}, "22bPsP2jCgbLUvh82U0Z3M": {"s": 550603016, "d": 198105}, "28tIMaewZuGR8urkvFhQyA": {"s": 18011001, "d": 5852}, "2913xXOVAIDAqxzV2g4VcU": {"s": 147317426, "d": 72247}, "2BUTSRKPGRsyc9FnsC5Udd": {"s": 18483026, "d": 13398}, "2CYVETnhM9aytqrazYYwrK": {"s": 452875268, "d": 93913}, "2CnjDMdpRjlWv04Xk3s6MW": {"s": 87177813, "d": 38769}, "2EFZ9emtKWEglWUQGEQ3P9": {"s": 83665595, "d": 32140}, "4ojxSyrEraN7d46BMBPThZ": {"s": 447332040, "d": 5852}, "2F3N9tdombb64aW6VtZOdo": {"s": 484082535, "d": 206720}, "2IprIjGNRlj3TfqUWCAo0C": {"s": 38477516, "d": 34100}, "2JoJrsEV15OzbijS47lids": {"s": 69844483, "d": 15897}, "2L09RYwH5Pjzca6PmbUAw3": {"s": 351027618, "d": 101806}, "2M4tVhRXucLE9M3STv21Yi": {"s": 28422549, "d": 4216}, "2NGGvVcfb2m2NbVaXHC3gb": {"s": 1013516, "d": 5872}, "2NlmmAjGYrrjAp0MED5rGx": {"s": 708736945, "d": 198509}, "2NmsngXHeC1GQ9wWrzhOMf": {"s": 613631552, "d": 6174}, "2NnrAdjE9cPdMklonMBuAv": {"s": 42618941, "d": 4189}, "2OzhQlSqBEmt7hmkYxfT6m": {"s": 1057055482, "d": 508866}, "2PGIFYRG1XWsPqNG14hgD1": {"s": 4848148, "d": 1154}, "2QA3IixpRcKyOdG7XDzRgv": {"s": 39896603, "d": 9176}, "2QDyYdZyhlP2fp79KZX8Bi": {"s": 272725002, "d": 4742}, "2QrQCMel6v2JiLxqrg4p2O": {"s": 60584285, "d": 14588}, "2R7C9dDqv1UPycvepBFziA": {"s": 27711837, "d": 3341}, "2RJnNdu4pb3MypbBroHU0T": {"s": 78245155, "d": 26889}, "2Rk4JlNc2TPmZe2af99d45": {"s": 957891408, "d": 103828}, "2Sy2oGjP5RYB4cLVoDU0Gz": {"s": 50770941, "d": 9213}, "2TEQvxxQabwLQMqWMg1qGu": {"s": 151829094, "d": 1330779}, "2ULNeSomDxVNmdDy8VxEBU": {"s": 448248191, "d": 86335}, "2VuqMjgoKaOHNM8HpxtXKx": {"s": 360135300, "d": 100345}, "2XXwLdtuAcE0HSCu61ijAb": {"s": 373145095, "d": 173742}, "2YWtcWi3a83pdEg3Gif4Pd": {"s": 334814328, "d": 64599}, "2ZoOmCSgj0ypVAmGd1ve4y": {"s": 44942256, "d": 9822}, "2bzUVEvpZ7At5cYz1kOLI9": {"s": 83167645, "d": 36401}, "2dgFqt3w9xIQRjhPtwNk3D": {"s": 356336825, "d": 82767}, "2fgiBCtbWo8pijF6M7pN1i": {"s": 14549345, "d": 4297}, "2hmafYGj1CXYKIYcMnX4lj": {"s": 45975661, "d": 9942}, "2m3ObD945KvpE5y9A1eUWm": {"s": 73466769, "d": 18248}, "2msvOEbkK50foYf9BMXr2X": {"s": 29178129, "d": 6941}, "2nqio0SfWg6gh2eCtfuMa5": {"s": 128451880, "d": 25641}, "2o2sgVJIgFXk8GQjWTgI6U": {"s": 248587407, "d": 85542}, "2oWpe2L8ypC080BxpDVuTY": {"s": 38430833, "d": 11327}, "2r9CbjYgFhtAmcFv1cSquB": {"s": 119615782, "d": 46758}, "6KJqZcs9XDgVck7Lg9QOTC": {"s": 405262607, "d": 5201}, "2wtHlpYSgC7xEdD3DrSHNL": {"s": 47132347, "d": 6129}, "2x0WlnmfG39ZuDmstl9xfX": {"s": 600527872, "d": 113166}, "2x3mwb96B6TquRqMtbxUE1": {"s": 142925488, "d": 1171821}, "2y5aJvzXhHPA94U5GFAcXe": {"s": 2012315025, "d": 568538}, "2yLa0QULdQr0qAIvVwN6B5": {"s": 964896508, "d": 275963}, "2yceD2hx5HhOLgkm1CITCi": {"s": 21922317, "d": 7344}, "2zfgVd034GlUvk7LqBHl6u": {"s": 143787507, "d": 15584}, "30Y4CV7A6YqtQtTTo7Ue4j": {"s": 134078548, "d": 28246}, "31JVjy3XWnh6C2zf4kLCXN": {"s": 8591226, "d": 7021}, "32mVHdy0bi1XKgr0ajsBlG": {"s": 244976976, "d": 55441}, "34V9RiEPe8MNdU32qJsJa1": {"s": 73490287, "d": 11568}, "35rdVq36LMHQX0Suw9a6tK": {"s": 151493146, "d": 39205}, "36a08nLG1xazGaaVKK0vv7": {"s": 9514536, "d": 2265}, "37jfioVu3Bd2Du9bteXNDU": {"s": 41420048, "d": 18985}, "3AKV7Mvo2Mx4tb39iPvPlT": {"s": 197963907, "d": 1755318}, "3CCRVu4F91Qp2mnGjmWBrf": {"s": 267634900, "d": 93051}, "3CWq0pAKKTWb0K4yiglDc4": {"s": 357320051, "d": 154937}, "3EPgWM1zfTSzEc0z4AwWTM": {"s": 31599888, "d": 22514}, "3ExweHKZF9B752DPQByRVT": {"s": 56670935, "d": 11077}, "3JilapcaOXzjR9gtvCY8FO": {"s": 96760854, "d": 16482}, "3K2es3gElMRJ3qvmPW442g": {"s": 152433761, "d": 19387}, "3MytWN8L7shNYzGl4tAKRp": {"s": 177276695, "d": 59294}, "3NMrVbIVWT3fPXBj0rNDKG": {"s": 308706662, "d": 103198}, "3O5osWf1rSoKMwe6E9ZaXP": {"s": 180706922, "d": 1927282}, "3RNDw7yywLNyawDKV99hTx": {"s": 11146560, "d": 2026}, "3RaT22zZsxVYxxKR7TAaYF": {"s": 336589256, "d": 78628}, "3RauEVgRgj1IuWdJ9fDs70": {"s": 968254212, "d": 185213}, "3S7HNKPakdwNEBFIVTL6dZ": {"s": 139716503, "d": 35892}, "3Vevii7qKqrmW8CcyzBHDl": {"s": 391548191, "d": 157513}, "3YkNIrAvbKNrrwwEd7NVLl": {"s": 320657319, "d": 249338}, "3ZVFcD8Wlw9T9klGqmJf9F": {"s": 304865889, "d": 98886}, "3eX0NZfLtGzoLUxPNvRfqm": {"s": 580387772, "d": 171753}, "3fGnrtrtL1IHSX9t4DKOYf": {"s": 80450929, "d": 15567}, "3fO566xJgwxIa3qGCGBvIC": {"s": 231483964, "d": 108774}, "3hlGuz3loYoLfI3bpwieWq": {"s": 160027907, "d": 73125}, "3i9UVldZOE0aD0JnyfAZZ0": {"s": 324170305, "d": 47820}, "3k7ne7VmH43ZPWxPdvPUgR": {"s": 223376995, "d": 67537}, "3kfgJql90tzgoxByioAMXR": {"s": 56167052, "d": 6438}, "3lXekiVK1ZPZbKconsys73": {"s": 51210372, "d": 8367}, "3nRmDz7qGCvsMS30rGGY0x": {"s": 282803994, "d": 90652}, "3nsfB1vus2qaloUdcBZvDu": {"s": 355037070, "d": 154875}, "3oF7Or7T35yhQbGxbCGvRX": {"s": 44293156, "d": 7013}, "3oGVx9RBmiYGv5ZCecWLkx": {"s": 117963842, "d": 31152}, "3pHkh7d0lzM2AldUtz2x37": {"s": 522942679, "d": 168035}, "3pv7Q5v2dpdefwdWIvE7yH": {"s": 211620126, "d": 94987}, "3qoftcUZaUOncvIYjFSPdE": {"s": 684132756, "d": 166818}, "3r9fAceWmaDFvbNiTnFiLr": {"s": 1153568, "d": 6665}, "3rWDp9tBPQR9z6U5YyRSK4": {"s": 816802529, "d": 171437}, "3sW3oSbzsfecv9XoUdGs7h": {"s": 471867179, "d": 245914}, "3tGq7hWDCtrnL83y5OGual": {"s": 23901719, "d": 4840}, "3xYJScVfxByb61dYHTwiby": {"s": 268554325, "d": 104454}, "3yII7UwgLF6K5zW3xad3MP": {"s": 391850689, "d": 109080}, "3yNJkriPzWjkkDAWHIAVUq": {"s": 78362683, "d": 19977}, "3yWuTOYDztXjZxdE2cIRUa": {"s": 279456878, "d": 3390317}, "3z6XUommYDWPHeFhmhhT6j": {"s": 263109444, "d": 132403}, "3zMDGj4D8ogaYgAIZPeU7S": {"s": 154406819, "d": 86748}, "40PXEOFLJc7UIpLMrhSfW1": {"s": 120284955, "d": 15538}, "42TAweWJJ9YlQ47T5nesu5": {"s": 691063, "d": 3950}, "43rA71bccXFGD4C8GOpIlN": {"s": 399565616, "d": 140935}, "43y1WpBdnEy5TR9aZoSQL9": {"s": 130167042, "d": 44476}, "45R112Jz5hQeKgITXgSXzs": {"s": 974757170, "d": 214204}, "45wMBGri1PORPjM9PwFfrS": {"s": 335178797, "d": 194357}, "46NGAvL695VnbcSeTmQWmM": {"s": 203832369, "d": 32494}, "48A0aShHlovDfTMucMrE66": {"s": 141181238, "d": 23956}, "4A2LfnduSTsE8u0ecYROxE": {"s": 156001011, "d": 23666}, "4A4A6dwl5DqdqrZaEtKGPR": {"s": 1119303956, "d": 278466}, "4ABYxlb92WBIjHu7TIKmml": {"s": 114187460, "d": 28367}, "4AYtqFyFbX0Xkc2wtcygTr": {"s": 173060225, "d": 36981}, "4CHpVfAhuxNJ3ibExe6kxO": {"s": 131325478, "d": 16974}, "4CkgMiMqZ5JzW9iYXSTMTL": {"s": 277891129, "d": 79243}, "4D7BCuvgdJlYvlX5WlN54t": {"s": 805971946, "d": 310206}, "4EF6IyONolQy0bIQXm2EmX": {"s": 134944330, "d": 47421}, "4JQm7ebhsrt10wmrP6AfXL": {"s": 6310374, "d": 489}, "4GBbcyrbDzwRtQjrsDRywK": {"s": 311563795, "d": 126633}, "4IQkfUsrwXol38VV3U7t7T": {"s": 164987897, "d": 33550}, "4MGexoZc12lqE0hYkq9YYx": {"s": 27175681, "d": 15598}, "4N419mmxYybTfAECy5j4dw": {"s": 50213403, "d": 6602}, "4OAuvHryIVv4kMDNSLuPt6": {"s": 290291621, "d": 2286935}, "4OmFmE0fzcMG6g0Y8p4eSD": {"s": 189150813, "d": 66668}, "4R2kfaDFhslZEMJqAFNpdd": {"s": 1959411769, "d": 22514}, "4TtyvyI42C0KFnbDZvNC8Y": {"s": 4837099, "d": 478}, "4VbErhGDMTnvPAnt5z70DL": {"s": 2454051, "d": 486}, "4WBEj8TeGtRPNJdOmT3WJW": {"s": 345847875, "d": 151674}, "4XMP3zVxrnr58T0tjIHvpR": {"s": 267290937, "d": 25799}, "4XiypEn8iKbeP1TbTqdfk5": {"s": 4347140, "d": 1338}, "4YHHz3VIXgNDGdoL9xC1tx": {"s": 14066878, "d": 4693}, "4YrpqEBNuz7IMsZtUP6bNQ": {"s": 9323187, "d": 1409}, "4bBDkw2KBMX0tcgAaXC83Q": {"s": 371716327, "d": 149486}, "4bXCcoesMt8u99xMsbLr9U": {"s": 211373818, "d": 27668}, "4cOWq0cVsKjxaQpRMbDoH1": {"s": 17163447, "d": 5201}, "4d9PtIEVij9jW5OaLinH66": {"s": 164259898, "d": 54141}, "4dgf2DYVJbtmy8zAYLs4c7": {"s": 750472175, "d": 435997}, "4e3ZNTAV6PCrdYMUrUlMpQ": {"s": 119618380, "d": 29890}, "4e5ayHsOLJNLTGfjau2mEw": {"s": 97159990, "d": 22155}, "4evLyY5Ue1Wesc61t2KXAU": {"s": 55069527, "d": 15177}, "4fWDgRZa0GKE5KZNhE9MQa": {"s": 54272842, "d": 8036}, "4hqJ4bSlYJOXb6Z4SRmzxs": {"s": 206156246, "d": 70164}, "4i6cwNY6oIUU2XZxPIw82Y": {"s": 110842202, "d": 20463}, "4lD3RXyvHpJsM3BhIEC4aA": {"s": 13298967, "d": 3352}, "4mKye6Z1kXuKolzMkJoKFA": {"s": 241475098, "d": 250358}, "4mqgn90sCeVSYqcoftTQTd": {"s": 18994274, "d": 2354}, "4pFvEWbjBpPUdYRQly0THs": {"s": 34424891, "d": 4824}, "4pJi1rVt9GNegU9kywjg4z": {"s": 44463920, "d": 12606}, "4pNApnaUWAL2J4KO2eqokq": {"s": 149936915, "d": 58048}, "4pvb0WLRcMtbPGmtejJJ6y": {"s": 1078354258, "d": 16870}, "4qUijfYU8EoIWiY6oSyrgT": {"s": 68908036, "d": 10950}, "4qmFC3Jz5aQ0erlk2OSi2X": {"s": 116084433, "d": 906417}, "4qyalTRMRH5YuEntvvMvq0": {"s": 45866486, "d": 6511}, "4s8BIKx4Zh6ryAEz8RTlaU": {"s": 129638270, "d": 37334}, "4svZDCRz4cJoneBpjpx8DJ": {"s": 554490653, "d": 107752}, "4tMzIAFTFdqGBQLdfbPces": {"s": 119754294, "d": 37609}, "4txojlesMFQZGWxwz2EeqB": {"s": 346486160, "d": 100661}, "4uuEGH5SVuzkkSFjo2DEiY": {"s": 89723011, "d": 18598}, "4y5bvROuBDPr5fuwXbIBZR": {"s": 799112528, "d": 189211}, "4yf9OivCH2lmQWN8mzpCC6": {"s": 128661435, "d": 18669}, "4yyKppX85ZkmlGOC2toBZA": {"s": 12815024, "d": 4228}, "4zmKGsrXjLmljb5fTaBTot": {"s": 282119469, "d": 113168}, "50ho0AOvkm8E5l8zf7OfJI": {"s": 13097090, "d": 12046}, "51A8eKvvZz9uydvIZ7xRSV": {"s": 46614919, "d": 9875}, "53iuhJlwXhSER5J2IYYv1W": {"s": 425111418, "d": 6664978}, "550erGcdD9n6PnwxrvYqZT": {"s": 114897019, "d": 24686}, "560uQyz3p5G9WdnMX39xc6": {"s": 20194841, "d": 6174}, "59KOoHFcw5XfICnO57holu": {"s": 126256604, "d": 69408}, "5AsmAjBSSQjRPWgAYIp8tm": {"s": 33821353, "d": 3857}, "5BK0uqwY9DNfZ630STAEaq": {"s": 346937893, "d": 85065}, "5Bedn0svl0ZD7RGmJkmKKw": {"s": 198886011, "d": 104317}, "5EwypOO9NEI7MvjPOYZtWk": {"s": 676114, "d": 3879}, "5XkJj6sV2XLMaURdmdXgNx": {"s": 10364068, "d": 2236}, "5G9AVKld9q7DCrmoY42raf": {"s": 25336388, "d": 2909}, "5KByGq0JijSSDcy0qzuINs": {"s": 16467570, "d": 5176}, "5M787RexsAiVYjQusM98CV": {"s": 207677114, "d": 65005}, "5OOd01o2YS1QFwdpVLds3r": {"s": 44330838, "d": 9383}, "5PxFv9yJEg9dxvbZggykro": {"s": 236142431, "d": 58445}, "5QKhg4r4Ibt0LVTmWEXTEg": {"s": 42858053, "d": 6614}, "5QUIK7ZtziW8kGWo8RqopF": {"s": 410214427, "d": 120702}, "5RaBeejGtdPEszYEKYECs2": {"s": 39346337, "d": 4989}, "5SkuikJwvwfEvNyCepGkq3": {"s": 1063304, "d": 6092}, "5VDHMi7own9vDZjiwDES1e": {"s": 15473775, "d": 6999}, "5VwFkx7JOimOGTYfha5rs1": {"s": 66138489, "d": 7563}, "5YL553x8sHderRBDlm3NM3": {"s": 143336261, "d": 62759}, "5YbZZ2gYfvW1UvHHF4pVaD": {"s": 44588671, "d": 7149}, "5YqltLsjdqFtvqE7Nrysvs": {"s": 467842412, "d": 108731}, "5chnRTB9qMK3W1M41SnU9s": {"s": 174329667, "d": 54088}, "5d2Kn9oAAh9S2EbyCo1i52": {"s": 58807735, "d": 8935}, "5eGX87IiKsGuzS3iw4CfCX": {"s": 80033919, "d": 10621}, "5eXgqtg3T8Av0m1FUaGHex": {"s": 151411865, "d": 1370229}, "5fOV54t6mMYv3H9CsnvU81": {"s": 9306957, "d": 2339}, "5gRYrtvyVyaCRvLt56OfuV": {"s": 164395362, "d": 21363}, "5hQSXkFgbxjZo9uCwd11so": {"s": 341092092, "d": 209838}, "5jAIouBES8LWMiriuNq170": {"s": 70438764, "d": 23587}, "5jQI2r1RdgtuT8S3iG8zFC": {"s": 860058358, "d": 156926}, "5k9RjjuYyOMCLL81U8FaHT": {"s": 1303315, "d": 7400}, "5kHMfzgLZP95O9NBy0ku4v": {"s": 328853224, "d": 69411}, "5kI4eCXXzyuIUXjQra0Cxi": {"s": 453421981, "d": 4385}, "5kYFVSQoPu7yRpfiHBwMUk": {"s": 59347781, "d": 7801}, "5l6GqSxplqnZbLg0LTPQeG": {"s": 474146623, "d": 143291}, "5lA0yK8S5tP3xoaRMCp4Ug": {"s": 4560123, "d": 542}, "5mdNyCS7ttVcAyVYOIFEjs": {"s": 29528578, "d": 11693}, "5og4Qzt92jJzVDkOtSEilb": {"s": 349208587, "d": 112923}, "5tWxKWq1DSP1s9WQ5PWuqu": {"s": 231620496, "d": 56147}, "5vyxXfD5gLlyPxGZMEjtmd": {"s": 138398644, "d": 34798}, "5xPsybHWRHbTYO44xnREY5": {"s": 1060144721, "d": 306317}, "5xXqyjLicvEpch72qEryFT": {"s": 71827710, "d": 1155168}, "5ylJtmaWPJ33cW3En7WOu0": {"s": 147074837, "d": 1170545}, "5yrrh7VYFMCNjUOIMzGNp5": {"s": 803604, "d": 4799}, "60hGQrn24APqEFSLObLeDc": {"s": 276621554, "d": 61678}, "60oZARTE1kCh5ntBfeO1XB": {"s": 6192854, "d": 48743}, "62E2nR0od0M5HYxuYLaDz7": {"s": 195244825, "d": 86793}, "62HoDY1Km6lm47haFpUn9c": {"s": 134684463, "d": 1004309}, "62V2ZHslgQV98gH4AuVXnr": {"s": 131366530, "d": 1034502}, "62rlxI6g2PNaWsHoiRryto": {"s": 27366420, "d": 4434}, "64FzgoLZ3oXu2SriZblHic": {"s": 142748391, "d": 59183}, "670fUmXf4KQekzbEgaXyPA": {"s": 219965742, "d": 77119}, "6AtZLIzUINvExIUy4QhdjP": {"s": 482508744, "d": 105879}, "6C0H8ts9M6deezz0yYR6LK": {"s": 20005884, "d": 4473}, "6F67FNdOBNMFzxdj1CQ5pL": {"s": 17746976, "d": 5657}, "6FJemhBlVTGTCgrrrLam3D": {"s": 850322, "d": 4702}, "6GXgd1BPD9bUpqw5AntGV5": {"s": 149604674, "d": 53628}, "6HRsJu8vcnzYDN4t0570FY": {"s": 114894499, "d": 40064}, "6IG3sQ8s9nfk6TUlVzRhbN": {"s": 558370790, "d": 130512}, "6IH2Z54gYPLqgJtxZjX80i": {"s": 80566396, "d": 6423}, "6INztpNwOTlfSKTuPo0HOP": {"s": 93293625, "d": 59975}, "6JNM6pLKbXMGG2opeExCb2": {"s": 791361, "d": 4170}, "6K0CJLVXqbGMeJSmJ4ENKK": {"s": 43350688, "d": 9765}, "6LZaxlycSWrJZ4Volb25qx": {"s": 246181538, "d": 32016}, "6M9ppdfFjR1AbpUl3Y8DcV": {"s": 152197318, "d": 38889}, "6MWoRt97mnSTXZhu3ggi9C": {"s": 243770492, "d": 4801}, "6N1K5OVVCopBjGViHs2IvP": {"s": 219948075, "d": 57199}, "6NFyWDv5CjfwuzoCkw47Xf": {"s": 1248182616, "d": 363761}, "6NUy8xajng5zMSGJRKniAG": {"s": 854269, "d": 4963}, "6ON9UuIq49xXY9GPmHIYRp": {"s": 68046585, "d": 16211}, "6PlBKImSl4AZoxBU7F649D": {"s": 706530, "d": 178845}, "6RRNNciQGZEXnqk8SQ9yv5": {"s": 1100066173, "d": 162621}, "6SYwJcqaltK2WFRmD1unUV": {"s": 8425945, "d": 1226}, "6VsvKPJ4xjVNKpI8VVZ3SV": {"s": 523062160, "d": 5176}, "6WWvcA62QlnRguluWAk6bv": {"s": 28093276, "d": 4088}, "6XDBA3QWX51lDJ0oZbaJJN": {"s": 113719351, "d": 17177}, "6YvqWjhGD8mB5QXcbcUKtx": {"s": 1093654920, "d": 454724}, "6aLOekfwbytwWvQftxTEF0": {"s": 239789793, "d": 37252}, "6cf6rLb8qcklvJv90W6HCW": {"s": 24862329, "d": 3637}, "6dTA6y0C2ReQklntzZl8l3": {"s": 139399868, "d": 40226}, "6iWMI5oOhWrDbLbjmwTWFq": {"s": 162686995, "d": 20004}, "6iiAfo4wTA2CVC3Uwx9uh8": {"s": 94496090, "d": 22374}, "6kl8thRysTeVV3WvKxgZAy": {"s": 400968774, "d": 146703}, "6lzc0Al0zfZOIFsFvBS1ki": {"s": 155925893, "d": 38291}, "6mqyTq948oap5AkyTsd6XF": {"s": 20070329, "d": 6737}, "6oVxXO5oQ4pTpO8RSnkzvv": {"s": 493545539, "d": 562780}, "6ovFJkdau79DuXEvQjPaNH": {"s": 25520964, "d": 4578}, "6pYNq0ZwpPVazKzsqpf0G8": {"s": 219397921, "d": 64976}, "6qAcApH8obo8eqatCKUHd9": {"s": 131216896, "d": 31736}, "6rZVy6FIG7lSJQMFXHo12z": {"s": 317556127, "d": 58557}, "6sQckd3Z8NPxVVKUnavY1F": {"s": 326452432, "d": 107184}, "6vLpy7UPYuOa75Bkqocrcw": {"s": 34591885, "d": 5013}, "6wfugRLamFsTRbPcCpNnP7": {"s": 188774761, "d": 31997}, "6xsEAm6w9oMQYYg3jkEkMT": {"s": 218096168, "d": 49932}, "6zV8AVM9eVfdG7Qahwd64R": {"s": 141919979, "d": 34539}, "71CBDRKmF2VeRKYMG1DFBh": {"s": 238930198, "d": 78373}, "71IScwIe7bcIlpnlkbKVQw": {"s": 14902076, "d": 11686}, "72GIZuUXo14oyrS0si3Rgc": {"s": 7927634, "d": 1034}, "72jCZdH0Lhg93z6Z4hBjgj": {"s": 1036110917, "d": 432868}, "733OhaXQIHY7BKtY3vnSkn": {"s": 114880018, "d": 44749}, "73OX8GdpOeGzKC6OvGSbsv": {"s": 54349510, "d": 12274}, "73W5aXorr5vxrySFcoZqIN": {"s": 173790850, "d": 80967}, "73YUReisjb3A9ActdLLjJQ": {"s": 233191510, "d": 71660}, "73qMN9bXy7MSPwwGfH3wQr": {"s": 129044168, "d": 49113}, "77VotUUL79U10TAnYdqwvr": {"s": 80396461, "d": 18397}, "77p4fRpoeiZMtUy3P9kN21": {"s": 15496382, "d": 1648}, "77sMIMlNaSURUAXq5coCxE": {"s": 339281030, "d": 1766430}, "786NsUYn4GGUf8AOt0SQhP": {"s": 66466114, "d": 10609}, "79uDOz0zuuWS7HWxzMmTa2": {"s": 281415627, "d": 105482}, "7A2cNLRT0YJc1yjxHlKihs": {"s": 90550624, "d": 22801}, "7AEAGTc8cReDqcbPoY9gwo": {"s": 771410426, "d": 164226}, "7BT9K9BDqq6HI2oWH5UMZQ": {"s": 17669041, "d": 2186}, "7Bjf96uNizpvXLvNyOJpst": {"s": 18059500, "d": 2422}, "7C0w28EsX0Um2FrZs9gso2": {"s": 152679359, "d": 32516}, "7F5oktn5YOsR9eR5YsFtqb": {"s": 257324543, "d": 75300}, "7FKbTRXXIWVFQmPH8zGfU0": {"s": 23459619, "d": 2634}, "7G0gBu6nLdhFDPRLc0HdDG": {"s": 262401354, "d": 79116}, "7G6TDmGJXDoBaV6NGj3Yic": {"s": 774582458, "d": 241421}, "7GZ3KDorsc1yWndEtzGTjf": {"s": 7626826, "d": 8704}, "7HC7R2D8WjXVcUHJyEGjRs": {"s": 85958790, "d": 18621}, "7HuBDWi18s4aJM8UFnNheH": {"s": 351945592, "d": 112586}, "7I7JbDv63ZJJsSi24DyJrz": {"s": 325030755, "d": 103005}, "7J4b3LVCIGO4CMBDFLPoP6": {"s": 113230085, "d": 30143}, "7MbT4I8qGntX4fMdqMQgke": {"s": 269923147, "d": 4693}, "7N015NTIWGjQDddHUdHPoO": {"s": 61122291, "d": 16870}, "7an1exwMnfYRcdVQm0yDev": {"s": 55785958, "d": 13514}, "7dXKdjpOaH2iwfFKmUj7aq": {"s": 158404026, "d": 19960}, "7eQj6r5PIdYKEIZjucBMcq": {"s": 109940012, "d": 22754}, "7eResoqEJJAVTkQYSqvO3P": {"s": 99128472, "d": 17681}, "7gdwoOmi258QJq0hmQ4hto": {"s": 303782536, "d": 56143}, "7kjSmkSo15pHlkb0mOQtfj": {"s": 4354288, "d": 1290}, "7kt9e9LFSpN1zQtYEl19o1": {"s": 573286707, "d": 12215}, "7nWui6jiMM2m9qFmET1Mtj": {"s": 55897515, "d": 14402}, "7pM01Cfj8vt7z3qI2TveNT": {"s": 2025293, "d": 501}, "7qEUFOVcxRI19tbT68JcYK": {"s": 222143071, "d": 119002}, "7ryS0xBZNYjQqql34GCkDp": {"s": 33236595, "d": 14943}, "7vvIpJZye5cRR6De1LKM0m": {"s": 71602177, "d": 8966}, "7wo2UNeQBowm28hfAJsEMz": {"s": 18447389, "d": 7979}}